curlquest/__init__.py
curlquest/defaults.py
curlquest/dict.py
curlquest/helper.py
curlquest/models.py
curlquest/sessions.py
curlquest-0.1.1.dist-info/LICENSE
curlquest-0.1.1.dist-info/METADATA
curlquest-0.1.1.dist-info/WHEEL
curlquest-0.1.1.dist-info/RECORD
