Metadata-Version: 2.1
Name: curlquest
Version: 0.1.1
Summary: A user-friendly wrapper for pycurl that simplifies HTTP requests (fork of request_curl with a few changes)
Home-page: https://github.com/Sygmei/curlquest
License: MIT
Author: Mauritz Uphoff
Author-email: mauritz.uphoff@hs-osnabrueck.de
Maintainer: Mauritz Uphoff
Requires-Python: >=3.7,<4.0
Classifier: License :: OSI Approved :: MIT License
Classifier: Programming Language :: Python :: 3
Classifier: Programming Language :: Python :: 3.7
Classifier: Programming Language :: Python :: 3.8
Classifier: Programming Language :: Python :: 3.9
Classifier: Programming Language :: Python :: 3.10
Classifier: Programming Language :: Python :: 3.11
Classifier: Programming Language :: Python :: 3.12
Requires-Dist: Brotli (>=1.0.9,<2.0.0)
Requires-Dist: certifi (>=2024.2.2,<2025.0.0)
Requires-Dist: pycurl (>=7.45.2,<8.0.0)
Requires-Dist: requests (>=2.28.1,<3.0.0)
Project-URL: Documentation, https://github.com/Sygmei/curlquest/blob/main/README.md
Project-URL: Repository, https://github.com/Sygmei/curlquest
